Metadata-Version: 2.1
Name: Virtual-Clapperboard
Version: 0.1.0
Summary: A virtual clapperboard program for syncing an audio tone with a visual cue on the screen. Written in Python & Pygame.
Home-page: https://github.com/asweigart/virtualclapperboard
Author: Al Sweigart
Author-email: al@inventwithpython.com
License: MIT
Platform: UNKNOWN
Classifier: License :: OSI Approved :: MIT License
Classifier: Programming Language :: Python
Classifier: Programming Language :: Python :: 3
Classifier: Programming Language :: Python :: 3.5
Classifier: Programming Language :: Python :: 3.6
Classifier: Programming Language :: Python :: 3.7
Classifier: Programming Language :: Python :: 3.8
Classifier: Programming Language :: Python :: 3.9
